ToJyutping/CustomList.py
ToJyutping/Jyutping.py
ToJyutping/PhonemesList.py
ToJyutping/ToJyutping.py
ToJyutping/Trie.py
ToJyutping/__init__.py
ToJyutping/trie.txt
ToJyutping/utils.py
ToJyutping/version.py
ToJyutping-3.2.0.dist-info/LICENSE
ToJyutping-3.2.0.dist-info/METADATA
ToJyutping-3.2.0.dist-info/WHEEL
ToJyutping-3.2.0.dist-info/top_level.txt
ToJyutping-3.2.0.dist-info/RECORD
