Metadata-Version: 2.1
Name: ToJyutping
Version: 3.2.0
Summary: 粵語拼音自動標註工具 Cantonese Pronunciation Automatic Labeling Tool
Home-page: https://github.com/CanCLID/ToJyutping
Author: Cantonese Computational Linguistics Infrastructure Development Workgroup
Author-email: support@jyutping.org
Project-URL: Bug Reports, https://github.com/CanCLID/ToJyutping/issues
Project-URL: Source, https://github.com/CanCLID/ToJyutping
Keywords: cantonese chinese chinese-characters jyutping linguistics natural-language-processing nlp romanization simplified-chinese traditional-chinese
Classifier: Development Status :: 4 - Beta
Classifier: Intended Audience :: Developers
Classifier: Topic :: Software Development :: Libraries :: Python Modules
Classifier: Topic :: Text Processing :: Linguistic
Classifier: Natural Language :: Cantonese
Classifier: Natural Language :: Chinese (Simplified)
Classifier: Natural Language :: Chinese (Traditional)
Classifier: Programming Language :: Python :: 3
Classifier: Programming Language :: Python :: 3.8
Classifier: Programming Language :: Python :: 3.9
Classifier: Programming Language :: Python :: 3.10
Classifier: Programming Language :: Python :: 3.11
Classifier: Programming Language :: Python :: 3.12
Requires-Python: >=3.8, <4
License-File: LICENSE
